{
    "key": "group_679ba0ba8601c",
    "title": "Global Product Message",
    "fields": [
        {
            "key": "field_679ba0bc82d18",
            "label": "Global Message Icon",
            "name": "global_message_icon",
            "aria-label": "",
            "type": "font-awesome",
            "instructions": "",
            "required": 0,
            "conditional_logic": 0,
            "wrapper": {
                "width": "30",
                "class": "",
                "id": ""
            },
            "icon_sets": [
                "solid",
                "sharp_solid",
                "regular",
                "sharp_regular",
                "light",
                "sharp_light",
                "thin",
                "sharp_thin",
                "sharp-duotone_solid",
                "duotone_solid",
                "fak",
                "brands"
            ],
            "custom_icon_set": "",
            "default_label": "",
            "default_value": "",
            "save_format": "class",
            "allow_null": 1,
            "show_preview": 1,
            "enqueue_fa": 1,
            "allow_in_bindings": 0,
            "fa_live_preview": "",
            "choices": []
        },
        {
            "key": "field_679bee4ebc366",
            "label": "Global Message Border Color",
            "name": "global_message_border_color",
            "aria-label": "",
            "type": "color_picker",
            "instructions": "",
            "required": false,
            "conditional_logic": 0,
            "wrapper": {
                "width": "30",
                "class": "",
                "id": ""
            },
            "default_value": "",
            "enable_opacity": false,
            "return_format": "string"
        },
        {
            "key": "field_679ba15c82d1a",
            "label": "Global Message Text",
            "name": "global_message_text",
            "aria-label": "",
            "type": "wysiwyg",
            "instructions": "",
            "required": 0,
            "conditional_logic": 0,
            "wrapper": {
                "width": "40",
                "class": "",
                "id": ""
            },
            "default_value": "",
            "allow_in_bindings": 0,
            "tabs": "all",
            "toolbar": "full",
            "media_upload": 0,
            "delay": 0
        }
    ],
    "location": [
        [
            {
                "param": "options_page",
                "operator": "==",
                "value": "acf-options"
            }
        ]
    ],
    "menu_order": 0,
    "position": "normal",
    "style": "default",
    "label_placement": "top",
    "instruction_placement": "label",
    "hide_on_screen": "",
    "active": true,
    "description": "",
    "show_in_rest": 0,
    "modified": 1738272385
}
